{"date":"2026-03-31","total":367,"list1":[{"symbol":"786","sector":"\u2014","price":56.22,"volume":329618,"price_5d_ago":42.67,"pct_5d":31.76,"pkr_5d":13.55,"avg_vol_5d":308204.0,"price_20d_ago":25.44,"pct_20d":120.99,"pkr_20d":30.78,"avg_vol_20d":292661.0},{"symbol":"CRTM","sector":"\u2014","price":41.29,"volume":770064,"price_5d_ago":54.7,"pct_5d":-24.52,"pkr_5d":-13.41,"avg_vol_5d":1330531.0,"price_20d_ago":21.93,"pct_20d":88.28,"pkr_20d":19.36,"avg_vol_20d":1422315.0},{"symbol":"SHDTR1","sector":"\u2014","price":1.53,"volume":1274489,"price_5d_ago":3.01,"pct_5d":-49.17,"pkr_5d":-1.48,"avg_vol_5d":771243.0,"price_20d_ago":1.01,"pct_20d":51.49,"pkr_20d":0.52,"avg_vol_20d":509038.0}],"list2":[{"symbol":"LSECLR","sector":"\u2014","price":0.36,"volume":6527725,"price_5d_ago":1.19,"pct_5d":-69.75,"pkr_5d":-0.83,"avg_vol_5d":2365270.0,"price_20d_ago":1.83,"pct_20d":-80.33,"pkr_20d":-1.47,"avg_vol_20d":3635290.0},{"symbol":"LSEVLR","sector":"\u2014","price":1.82,"volume":4341932,"price_5d_ago":3.31,"pct_5d":-45.02,"pkr_5d":-1.49,"avg_vol_5d":3623541.0,"price_20d_ago":5.79,"pct_20d":-68.57,"pkr_20d":-3.97,"avg_vol_20d":5433386.0},{"symbol":"ESBL","sector":"\u2014","price":9.91,"volume":411697,"price_5d_ago":13.0,"pct_5d":-23.77,"pkr_5d":-3.09,"avg_vol_5d":141692.0,"price_20d_ago":21.57,"pct_20d":-54.06,"pkr_20d":-11.66,"avg_vol_20d":171148.0}],"list3":[{"symbol":"WASLR","sector":"\u2014","price":0.79,"volume":40359533,"price_5d_ago":0.15,"pct_5d":426.67,"pkr_5d":0.64,"avg_vol_5d":15167642.0,"price_20d_ago":0.66,"pct_20d":19.7,"pkr_20d":0.13,"avg_vol_20d":8059129.0},{"symbol":"DEL","sector":"\u2014","price":21.12,"volume":245579,"price_5d_ago":15.35,"pct_5d":37.59,"pkr_5d":5.77,"avg_vol_5d":172451.0,"price_20d_ago":20.51,"pct_20d":2.97,"pkr_20d":0.61,"avg_vol_20d":93929.0},{"symbol":"786","sector":"\u2014","price":56.22,"volume":329618,"price_5d_ago":42.67,"pct_5d":31.76,"pkr_5d":13.55,"avg_vol_5d":308204.0,"price_20d_ago":25.44,"pct_20d":120.99,"pkr_20d":30.78,"avg_vol_20d":292661.0},{"symbol":"SGPL","sector":"\u2014","price":19.07,"volume":1286389,"price_5d_ago":14.7,"pct_5d":29.73,"pkr_5d":4.37,"avg_vol_5d":775077.0,"price_20d_ago":16.19,"pct_20d":17.79,"pkr_20d":2.88,"avg_vol_20d":395370.0}],"list4":[{"symbol":"LSECLR","sector":"\u2014","price":0.36,"volume":6527725,"price_5d_ago":1.19,"pct_5d":-69.75,"pkr_5d":-0.83,"avg_vol_5d":2365270.0,"price_20d_ago":1.83,"pct_20d":-80.33,"pkr_20d":-1.47,"avg_vol_20d":3635290.0},{"symbol":"SHDTR1","sector":"\u2014","price":1.53,"volume":1274489,"price_5d_ago":3.01,"pct_5d":-49.17,"pkr_5d":-1.48,"avg_vol_5d":771243.0,"price_20d_ago":1.01,"pct_20d":51.49,"pkr_20d":0.52,"avg_vol_20d":509038.0},{"symbol":"LSEVLR","sector":"\u2014","price":1.82,"volume":4341932,"price_5d_ago":3.31,"pct_5d":-45.02,"pkr_5d":-1.49,"avg_vol_5d":3623541.0,"price_20d_ago":5.79,"pct_20d":-68.57,"pkr_20d":-3.97,"avg_vol_20d":5433386.0},{"symbol":"786R","sector":"\u2014","price":2.47,"volume":198132,"price_5d_ago":4.34,"pct_5d":-43.09,"pkr_5d":-1.87,"avg_vol_5d":488134.0,"price_20d_ago":2.45,"pct_20d":0.82,"pkr_20d":0.02,"avg_vol_20d":598977.0},{"symbol":"DSFL","sector":"\u2014","price":0.9,"volume":3694000,"price_5d_ago":1.4,"pct_5d":-35.71,"pkr_5d":-0.5,"avg_vol_5d":3206900.0,"price_20d_ago":1.35,"pct_20d":-33.33,"pkr_20d":-0.45,"avg_vol_20d":1830000.0},{"symbol":"CRTM","sector":"\u2014","price":41.29,"volume":770064,"price_5d_ago":54.7,"pct_5d":-24.52,"pkr_5d":-13.41,"avg_vol_5d":1330531.0,"price_20d_ago":21.93,"pct_20d":88.28,"pkr_20d":19.36,"avg_vol_20d":1422315.0},{"symbol":"ESBL","sector":"\u2014","price":9.91,"volume":411697,"price_5d_ago":13.0,"pct_5d":-23.77,"pkr_5d":-3.09,"avg_vol_5d":141692.0,"price_20d_ago":21.57,"pct_20d":-54.06,"pkr_20d":-11.66,"avg_vol_20d":171148.0},{"symbol":"KSBP","sector":"\u2014","price":177.0,"volume":57629,"price_5d_ago":222.17,"pct_5d":-20.33,"pkr_5d":-45.17,"avg_vol_5d":319650.0,"price_20d_ago":170.15,"pct_20d":4.03,"pkr_20d":6.85,"avg_vol_20d":178832.0}],"list5":[],"list6":[{"symbol":"KSE100","sector":"\u2014","price":148743.32,"volume":232744006,"price_5d_ago":153966.36,"pct_5d":-3.39,"pkr_5d":-5223.05,"avg_vol_5d":289192571.0,"price_20d_ago":168062.17,"pct_20d":-11.5,"pkr_20d":-19318.85,"avg_vol_20d":269679498.0},{"symbol":"ALLSHR","sector":"\u2014","price":89074.97,"volume":432495736,"price_5d_ago":92315.63,"pct_5d":-3.51,"pkr_5d":-3240.66,"avg_vol_5d":499832317.0,"price_20d_ago":100418.83,"pct_20d":-11.3,"pkr_20d":-11343.86,"avg_vol_20d":479257401.0},{"symbol":"JSMFI","sector":"\u2014","price":37793.71,"volume":77030067,"price_5d_ago":39749.13,"pct_5d":-4.92,"pkr_5d":-1955.43,"avg_vol_5d":87862813.0,"price_20d_ago":44128.6,"pct_20d":-14.36,"pkr_20d":-6334.89,"avg_vol_20d":90676392.0},{"symbol":"PSXDIV20","sector":"\u2014","price":68302.62,"volume":47026764,"price_5d_ago":70191.78,"pct_5d":-2.69,"pkr_5d":-1889.16,"avg_vol_5d":53503013.0,"price_20d_ago":76962.27,"pct_20d":-11.25,"pkr_20d":-8659.65,"avg_vol_20d":59360809.0},{"symbol":"KMIALLSHR","sector":"\u2014","price":58342.49,"volume":204459082,"price_5d_ago":60009.47,"pct_5d":-2.78,"pkr_5d":-1666.97,"avg_vol_5d":271209309.0,"price_20d_ago":64292.17,"pct_20d":-9.25,"pkr_20d":-5949.67,"avg_vol_20d":251501471.0},{"symbol":"KSE30","sector":"\u2014","price":45031.6,"volume":99887579,"price_5d_ago":46696.53,"pct_5d":-3.57,"pkr_5d":-1664.92,"avg_vol_5d":120711459.0,"price_20d_ago":51322.39,"pct_20d":-12.26,"pkr_20d":-6290.79,"avg_vol_20d":125836598.0},{"symbol":"UPP9","sector":"\u2014","price":53092.56,"volume":17612972,"price_5d_ago":54744.11,"pct_5d":-3.02,"pkr_5d":-1651.55,"avg_vol_5d":24012739.0,"price_20d_ago":59136.23,"pct_20d":-10.22,"pkr_20d":-6043.67,"avg_vol_20d":24375275.0},{"symbol":"BKTI","sector":"\u2014","price":40694.56,"volume":42037062,"price_5d_ago":41978.02,"pct_5d":-3.06,"pkr_5d":-1283.46,"avg_vol_5d":41400950.0,"price_20d_ago":49115.42,"pct_20d":-17.15,"pkr_20d":-8420.86,"avg_vol_20d":46777198.0},{"symbol":"JSGBKTI","sector":"\u2014","price":61338.23,"volume":42037062,"price_5d_ago":62589.83,"pct_5d":-2.0,"pkr_5d":-1251.6,"avg_vol_5d":41401322.0,"price_20d_ago":70703.18,"pct_20d":-13.25,"pkr_20d":-9364.95,"avg_vol_20d":46777291.0},{"symbol":"NBPPGI","sector":"\u2014","price":43380.36,"volume":41944297,"price_5d_ago":44615.35,"pct_5d":-2.77,"pkr_5d":-1235.0,"avg_vol_5d":49175758.0,"price_20d_ago":47762.61,"pct_20d":-9.18,"pkr_20d":-4382.25,"avg_vol_20d":51411694.0},{"symbol":"MZNPI","sector":"\u2014","price":26557.37,"volume":39627140,"price_5d_ago":27709.86,"pct_5d":-4.16,"pkr_5d":-1152.5,"avg_vol_5d":50046339.0,"price_20d_ago":29199.19,"pct_20d":-9.05,"pkr_20d":-2641.82,"avg_vol_20d":53021609.0},{"symbol":"NITPGI","sector":"\u2014","price":39908.23,"volume":30048752,"price_5d_ago":41020.36,"pct_5d":-2.71,"pkr_5d":-1112.14,"avg_vol_5d":39923622.0,"price_20d_ago":43795.2,"pct_20d":-8.88,"pkr_20d":-3886.97,"avg_vol_20d":40991731.0},{"symbol":"OGTI","sector":"\u2014","price":31278.9,"volume":11430980,"price_5d_ago":32154.23,"pct_5d":-2.72,"pkr_5d":-875.33,"avg_vol_5d":14994332.0,"price_20d_ago":32316.78,"pct_20d":-3.21,"pkr_20d":-1037.88,"avg_vol_20d":15059694.0},{"symbol":"MII30","sector":"\u2014","price":19609.89,"volume":60772395,"price_5d_ago":20170.61,"pct_5d":-2.78,"pkr_5d":-560.72,"avg_vol_5d":81997819.0,"price_20d_ago":21488.31,"pct_20d":-8.74,"pkr_20d":-1878.42,"avg_vol_20d":79781470.0},{"symbol":"KSBP","sector":"\u2014","price":177.0,"volume":57629,"price_5d_ago":222.17,"pct_5d":-20.33,"pkr_5d":-45.17,"avg_vol_5d":319650.0,"price_20d_ago":170.15,"pct_20d":4.03,"pkr_20d":6.85,"avg_vol_20d":178832.0},{"symbol":"NRL","sector":"\u2014","price":291.18,"volume":685829,"price_5d_ago":330.36,"pct_5d":-11.86,"pkr_5d":-39.18,"avg_vol_5d":746228.0,"price_20d_ago":313.9,"pct_20d":-7.24,"pkr_20d":-22.72,"avg_vol_20d":915470.0},{"symbol":"UBL","sector":"\u2014","price":331.95,"volume":2524630,"price_5d_ago":370.0,"pct_5d":-10.28,"pkr_5d":-38.05,"avg_vol_5d":2183661.0,"price_20d_ago":439.8,"pct_20d":-24.52,"pkr_20d":-107.85,"avg_vol_20d":1980002.0},{"symbol":"PIOC","sector":"\u2014","price":207.02,"volume":81125,"price_5d_ago":230.16,"pct_5d":-10.05,"pkr_5d":-23.14,"avg_vol_5d":279363.0,"price_20d_ago":257.91,"pct_20d":-19.73,"pkr_20d":-50.89,"avg_vol_20d":325886.0},{"symbol":"AGP","sector":"\u2014","price":170.36,"volume":474945,"price_5d_ago":193.31,"pct_5d":-11.87,"pkr_5d":-22.95,"avg_vol_5d":959206.0,"price_20d_ago":218.09,"pct_20d":-21.89,"pkr_20d":-47.73,"avg_vol_20d":628727.0}]}