{"date":"2026-05-04","total":402,"list1":[{"symbol":"DFSM","sector":"\u2014","price":15.45,"volume":3018365,"price_5d_ago":12.5,"pct_5d":23.6,"pkr_5d":2.95,"avg_vol_5d":5387587.0,"price_20d_ago":5.92,"pct_20d":160.98,"pkr_20d":9.53,"avg_vol_20d":5172800.0},{"symbol":"MSCL","sector":"\u2014","price":42.3,"volume":229325,"price_5d_ago":26.25,"pct_5d":61.14,"pkr_5d":16.05,"avg_vol_5d":618856.0,"price_20d_ago":16.38,"pct_20d":158.24,"pkr_20d":25.92,"avg_vol_20d":431661.0},{"symbol":"SGPL","sector":"\u2014","price":49.16,"volume":5838753,"price_5d_ago":48.42,"pct_5d":1.53,"pkr_5d":0.74,"avg_vol_5d":3238798.0,"price_20d_ago":20.3,"pct_20d":142.17,"pkr_20d":28.86,"avg_vol_20d":2626576.0},{"symbol":"SPL","sector":"\u2014","price":72.4,"volume":367309,"price_5d_ago":54.45,"pct_5d":32.97,"pkr_5d":17.95,"avg_vol_5d":363750.0,"price_20d_ago":34.5,"pct_20d":109.86,"pkr_20d":37.9,"avg_vol_20d":135618.0},{"symbol":"ZTL","sector":"\u2014","price":19.4,"volume":4427394,"price_5d_ago":14.1,"pct_5d":37.59,"pkr_5d":5.3,"avg_vol_5d":2749330.0,"price_20d_ago":10.98,"pct_20d":76.68,"pkr_20d":8.42,"avg_vol_20d":825923.0},{"symbol":"TPLT","sector":"\u2014","price":13.36,"volume":1611504,"price_5d_ago":12.2,"pct_5d":9.51,"pkr_5d":1.16,"avg_vol_5d":1489125.0,"price_20d_ago":8.16,"pct_20d":63.73,"pkr_20d":5.2,"avg_vol_20d":2681263.0},{"symbol":"YOUW","sector":"\u2014","price":6.37,"volume":28340370,"price_5d_ago":7.6,"pct_5d":-16.18,"pkr_5d":-1.23,"avg_vol_5d":47079284.0,"price_20d_ago":3.98,"pct_20d":60.05,"pkr_20d":2.39,"avg_vol_20d":22945494.0},{"symbol":"MACFL","sector":"\u2014","price":32.3,"volume":1936109,"price_5d_ago":23.69,"pct_5d":36.34,"pkr_5d":8.61,"avg_vol_5d":4179162.0,"price_20d_ago":20.3,"pct_20d":59.11,"pkr_20d":12.0,"avg_vol_20d":1346974.0},{"symbol":"PIL","sector":"\u2014","price":5.96,"volume":1045492,"price_5d_ago":5.5,"pct_5d":8.36,"pkr_5d":0.46,"avg_vol_5d":961819.0,"price_20d_ago":3.75,"pct_20d":58.93,"pkr_20d":2.21,"avg_vol_20d":789596.0},{"symbol":"ASTM","sector":"\u2014","price":19.85,"volume":114260,"price_5d_ago":22.01,"pct_5d":-9.81,"pkr_5d":-2.16,"avg_vol_5d":259235.0,"price_20d_ago":12.55,"pct_20d":58.17,"pkr_20d":7.3,"avg_vol_20d":158045.0},{"symbol":"CRTM","sector":"\u2014","price":81.8,"volume":409828,"price_5d_ago":78.73,"pct_5d":3.9,"pkr_5d":3.07,"avg_vol_5d":731320.0,"price_20d_ago":52.44,"pct_20d":55.99,"pkr_20d":29.36,"avg_vol_20d":950475.0},{"symbol":"CSIL","sector":"\u2014","price":6.31,"volume":14606205,"price_5d_ago":6.95,"pct_5d":-9.21,"pkr_5d":-0.64,"avg_vol_5d":17686187.0,"price_20d_ago":4.09,"pct_20d":54.28,"pkr_20d":2.22,"avg_vol_20d":15206307.0},{"symbol":"UNITY","sector":"\u2014","price":12.28,"volume":20813504,"price_5d_ago":13.4,"pct_5d":-8.36,"pkr_5d":-1.12,"avg_vol_5d":20518160.0,"price_20d_ago":8.03,"pct_20d":52.93,"pkr_20d":4.25,"avg_vol_20d":35361941.0},{"symbol":"SHDTR1","sector":"\u2014","price":1.53,"volume":1274489,"price_5d_ago":3.01,"pct_5d":-49.17,"pkr_5d":-1.48,"avg_vol_5d":771243.0,"price_20d_ago":1.01,"pct_20d":51.49,"pkr_20d":0.52,"avg_vol_20d":509038.0}],"list2":[{"symbol":"LOADSR1","sector":"\u2014","price":0.09,"volume":21907705,"price_5d_ago":0.81,"pct_5d":-88.89,"pkr_5d":-0.72,"avg_vol_5d":8025721.0,"price_20d_ago":1.86,"pct_20d":-95.16,"pkr_20d":-1.77,"avg_vol_20d":6102166.0},{"symbol":"CLOV","sector":"\u2014","price":8.07,"volume":11134934,"price_5d_ago":8.07,"pct_5d":0.0,"pkr_5d":0.0,"avg_vol_5d":35200082.0,"price_20d_ago":61.81,"pct_20d":-86.94,"pkr_20d":-53.74,"avg_vol_20d":15861872.0},{"symbol":"TSBLR1","sector":"\u2014","price":0.18,"volume":50015407,"price_5d_ago":0.38,"pct_5d":-52.63,"pkr_5d":-0.2,"avg_vol_5d":25226331.0,"price_20d_ago":0.64,"pct_20d":-71.88,"pkr_20d":-0.46,"avg_vol_20d":22056028.0},{"symbol":"STL","sector":"\u2014","price":53.5,"volume":1224400,"price_5d_ago":59.3,"pct_5d":-9.78,"pkr_5d":-5.8,"avg_vol_5d":634545.0,"price_20d_ago":121.47,"pct_20d":-55.96,"pkr_20d":-67.97,"avg_vol_20d":1811739.0}],"list3":[{"symbol":"WASLR","sector":"\u2014","price":0.79,"volume":40359533,"price_5d_ago":0.15,"pct_5d":426.67,"pkr_5d":0.64,"avg_vol_5d":15167642.0,"price_20d_ago":0.66,"pct_20d":19.7,"pkr_20d":0.13,"avg_vol_20d":8059129.0},{"symbol":"MFFLR1","sector":"\u2014","price":9.01,"volume":164349,"price_5d_ago":4.01,"pct_5d":124.69,"pkr_5d":5.0,"avg_vol_5d":113438.0,"price_20d_ago":1.01,"pct_20d":792.08,"pkr_20d":8.0,"avg_vol_20d":63848.0},{"symbol":"MSCL","sector":"\u2014","price":42.3,"volume":229325,"price_5d_ago":26.25,"pct_5d":61.14,"pkr_5d":16.05,"avg_vol_5d":618856.0,"price_20d_ago":16.38,"pct_20d":158.24,"pkr_20d":25.92,"avg_vol_20d":431661.0},{"symbol":"ZTL","sector":"\u2014","price":19.4,"volume":4427394,"price_5d_ago":14.1,"pct_5d":37.59,"pkr_5d":5.3,"avg_vol_5d":2749330.0,"price_20d_ago":10.98,"pct_20d":76.68,"pkr_20d":8.42,"avg_vol_20d":825923.0},{"symbol":"MACFL","sector":"\u2014","price":32.3,"volume":1936109,"price_5d_ago":23.69,"pct_5d":36.34,"pkr_5d":8.61,"avg_vol_5d":4179162.0,"price_20d_ago":20.3,"pct_20d":59.11,"pkr_20d":12.0,"avg_vol_20d":1346974.0},{"symbol":"SPL","sector":"\u2014","price":72.4,"volume":367309,"price_5d_ago":54.45,"pct_5d":32.97,"pkr_5d":17.95,"avg_vol_5d":363750.0,"price_20d_ago":34.5,"pct_20d":109.86,"pkr_20d":37.9,"avg_vol_20d":135618.0},{"symbol":"GFIL","sector":"\u2014","price":29.99,"volume":314529,"price_5d_ago":22.88,"pct_5d":31.08,"pkr_5d":7.11,"avg_vol_5d":584042.0,"price_20d_ago":20.5,"pct_20d":46.29,"pkr_20d":9.49,"avg_vol_20d":290926.0},{"symbol":"DFSM","sector":"\u2014","price":15.45,"volume":3018365,"price_5d_ago":12.5,"pct_5d":23.6,"pkr_5d":2.95,"avg_vol_5d":5387587.0,"price_20d_ago":5.92,"pct_20d":160.98,"pkr_20d":9.53,"avg_vol_20d":5172800.0}],"list4":[{"symbol":"LOADSR1","sector":"\u2014","price":0.09,"volume":21907705,"price_5d_ago":0.81,"pct_5d":-88.89,"pkr_5d":-0.72,"avg_vol_5d":8025721.0,"price_20d_ago":1.86,"pct_20d":-95.16,"pkr_20d":-1.77,"avg_vol_20d":6102166.0},{"symbol":"TSBLR1","sector":"\u2014","price":0.18,"volume":50015407,"price_5d_ago":0.38,"pct_5d":-52.63,"pkr_5d":-0.2,"avg_vol_5d":25226331.0,"price_20d_ago":0.64,"pct_20d":-71.88,"pkr_20d":-0.46,"avg_vol_20d":22056028.0},{"symbol":"SHDTR1","sector":"\u2014","price":1.53,"volume":1274489,"price_5d_ago":3.01,"pct_5d":-49.17,"pkr_5d":-1.48,"avg_vol_5d":771243.0,"price_20d_ago":1.01,"pct_20d":51.49,"pkr_20d":0.52,"avg_vol_20d":509038.0},{"symbol":"ESBL","sector":"\u2014","price":13.13,"volume":933741,"price_5d_ago":18.15,"pct_5d":-27.66,"pkr_5d":-5.02,"avg_vol_5d":396883.0,"price_20d_ago":9.88,"pct_20d":32.89,"pkr_20d":3.25,"avg_vol_20d":593469.0},{"symbol":"TATM","sector":"\u2014","price":115.83,"volume":164033,"price_5d_ago":144.89,"pct_5d":-20.06,"pkr_5d":-29.06,"avg_vol_5d":106232.0,"price_20d_ago":88.6,"pct_20d":30.73,"pkr_20d":27.23,"avg_vol_20d":156075.0}],"list5":[{"symbol":"HCAR","sector":"\u2014","price":209.52,"volume":1727588,"price_5d_ago":185.0,"pct_5d":13.25,"pkr_5d":24.52,"avg_vol_5d":1716352.0,"price_20d_ago":158.77,"pct_20d":31.96,"pkr_20d":50.75,"avg_vol_20d":666821.0}],"list6":[{"symbol":"KMI30","sector":"\u2014","price":235367.68,"volume":199234437,"price_5d_ago":244986.87,"pct_5d":-3.93,"pkr_5d":-9619.19,"avg_vol_5d":198862264.0,"price_20d_ago":218271.12,"pct_20d":7.83,"pkr_20d":17096.56,"avg_vol_20d":193511582.0},{"symbol":"KSE100","sector":"\u2014","price":163948.94,"volume":355533559,"price_5d_ago":170672.04,"pct_5d":-3.94,"pkr_5d":-6723.1,"avg_vol_5d":422973035.0,"price_20d_ago":150398.71,"pct_20d":9.01,"pkr_20d":13550.23,"avg_vol_20d":425110502.0},{"symbol":"ALLSHR","sector":"\u2014","price":98115.06,"volume":693968724,"price_5d_ago":102034.88,"pct_5d":-3.84,"pkr_5d":-3919.82,"avg_vol_5d":911626811.0,"price_20d_ago":90084.08,"pct_20d":8.91,"pkr_20d":8030.98,"avg_vol_20d":961675817.0},{"symbol":"BKTI","sector":"\u2014","price":45631.49,"volume":55793631,"price_5d_ago":48171.04,"pct_5d":-5.27,"pkr_5d":-2539.55,"avg_vol_5d":84746947.0,"price_20d_ago":41775.34,"pct_20d":9.23,"pkr_20d":3856.16,"avg_vol_20d":86735151.0},{"symbol":"JSGBKTI","sector":"\u2014","price":69845.23,"volume":55793631,"price_5d_ago":72254.08,"pct_5d":-3.33,"pkr_5d":-2408.85,"avg_vol_5d":95516005.0,"price_20d_ago":63416.94,"pct_20d":10.14,"pkr_20d":6428.29,"avg_vol_20d":83832335.0},{"symbol":"UPP9","sector":"\u2014","price":58368.54,"volume":26946944,"price_5d_ago":60266.94,"pct_5d":-3.15,"pkr_5d":-1898.4,"avg_vol_5d":17196542.0,"price_20d_ago":53604.91,"pct_20d":8.89,"pkr_20d":4763.62,"avg_vol_20d":26079055.0},{"symbol":"NBPPGI","sector":"\u2014","price":47293.13,"volume":44408517,"price_5d_ago":49179.87,"pct_5d":-3.84,"pkr_5d":-1886.74,"avg_vol_5d":35216019.0,"price_20d_ago":44227.22,"pct_20d":6.93,"pkr_20d":3065.9,"avg_vol_20d":48668690.0},{"symbol":"KSE100PR","sector":"\u2014","price":50305.0,"volume":355533559,"price_5d_ago":52036.85,"pct_5d":-3.33,"pkr_5d":-1731.85,"avg_vol_5d":438771119.0,"price_20d_ago":46885.55,"pct_20d":7.29,"pkr_20d":3419.45,"avg_vol_20d":419771497.0},{"symbol":"JSMFI","sector":"\u2014","price":40003.24,"volume":38768264,"price_5d_ago":41482.19,"pct_5d":-3.57,"pkr_5d":-1478.94,"avg_vol_5d":30094304.0,"price_20d_ago":38394.3,"pct_20d":4.19,"pkr_20d":1608.95,"avg_vol_20d":39633188.0},{"symbol":"NITPGI","sector":"\u2014","price":43652.43,"volume":39097673,"price_5d_ago":45019.65,"pct_5d":-3.04,"pkr_5d":-1367.23,"avg_vol_5d":26140184.0,"price_20d_ago":40756.28,"pct_20d":7.11,"pkr_20d":2896.15,"avg_vol_20d":40571899.0},{"symbol":"MZNPI","sector":"\u2014","price":28905.37,"volume":64672471,"price_5d_ago":30087.82,"pct_5d":-3.93,"pkr_5d":-1182.44,"avg_vol_5d":47069857.0,"price_20d_ago":27022.04,"pct_20d":6.97,"pkr_20d":1883.33,"avg_vol_20d":66892116.0},{"symbol":"ACI","sector":"\u2014","price":21150.59,"volume":48255280,"price_5d_ago":22254.58,"pct_5d":-4.96,"pkr_5d":-1103.99,"avg_vol_5d":43734401.0,"price_20d_ago":18983.48,"pct_20d":11.42,"pkr_20d":2167.12,"avg_vol_20d":62796188.0},{"symbol":"MII30","sector":"\u2014","price":21217.22,"volume":85424841,"price_5d_ago":21836.61,"pct_5d":-2.84,"pkr_5d":-619.39,"avg_vol_5d":67582262.0,"price_20d_ago":19970.82,"pct_20d":6.24,"pkr_20d":1246.4,"avg_vol_20d":95476692.0},{"symbol":"SAZEW","sector":"\u2014","price":2040.07,"volume":503478,"price_5d_ago":2130.0,"pct_5d":-4.22,"pkr_5d":-89.93,"avg_vol_5d":339734.0,"price_20d_ago":1605.55,"pct_20d":27.06,"pkr_20d":434.52,"avg_vol_20d":531763.0},{"symbol":"ATRL","sector":"\u2014","price":898.24,"volume":702316,"price_5d_ago":971.99,"pct_5d":-7.59,"pkr_5d":-73.75,"avg_vol_5d":1257924.0,"price_20d_ago":864.56,"pct_20d":3.9,"pkr_20d":33.68,"avg_vol_20d":1459624.0},{"symbol":"GAL","sector":"\u2014","price":422.11,"volume":304674,"price_5d_ago":464.0,"pct_5d":-9.03,"pkr_5d":-41.89,"avg_vol_5d":263210.0,"price_20d_ago":300.21,"pct_20d":40.6,"pkr_20d":121.9,"avg_vol_20d":591836.0},{"symbol":"FEROZ","sector":"\u2014","price":374.97,"volume":395649,"price_5d_ago":415.0,"pct_5d":-9.65,"pkr_5d":-40.03,"avg_vol_5d":223587.0,"price_20d_ago":333.0,"pct_20d":12.6,"pkr_20d":41.97,"avg_vol_20d":94857.0},{"symbol":"NBP","sector":"\u2014","price":175.79,"volume":4621065,"price_5d_ago":213.9,"pct_5d":-17.82,"pkr_5d":-38.11,"avg_vol_5d":8696572.0,"price_20d_ago":170.0,"pct_20d":3.41,"pkr_20d":5.79,"avg_vol_20d":7915749.0},{"symbol":"PSO","sector":"\u2014","price":356.71,"volume":2064276,"price_5d_ago":394.44,"pct_5d":-9.57,"pkr_5d":-37.73,"avg_vol_5d":3580565.0,"price_20d_ago":337.21,"pct_20d":5.78,"pkr_20d":19.5,"avg_vol_20d":3612367.0},{"symbol":"UBL","sector":"\u2014","price":385.94,"volume":1096662,"price_5d_ago":417.88,"pct_5d":-7.64,"pkr_5d":-31.94,"avg_vol_5d":2334521.0,"price_20d_ago":326.76,"pct_20d":18.11,"pkr_20d":59.18,"avg_vol_20d":5438520.0},{"symbol":"TATM","sector":"\u2014","price":115.83,"volume":164033,"price_5d_ago":144.89,"pct_5d":-20.06,"pkr_5d":-29.06,"avg_vol_5d":106232.0,"price_20d_ago":88.6,"pct_20d":30.73,"pkr_20d":27.23,"avg_vol_20d":156075.0},{"symbol":"MARI","sector":"\u2014","price":632.74,"volume":431731,"price_5d_ago":661.0,"pct_5d":-4.28,"pkr_5d":-28.26,"avg_vol_5d":350412.0,"price_20d_ago":623.08,"pct_20d":1.55,"pkr_20d":9.66,"avg_vol_20d":861766.0},{"symbol":"GLAXO","sector":"\u2014","price":338.94,"volume":405076,"price_5d_ago":363.99,"pct_5d":-6.88,"pkr_5d":-25.05,"avg_vol_5d":311255.0,"price_20d_ago":324.3,"pct_20d":4.51,"pkr_20d":14.64,"avg_vol_20d":384050.0},{"symbol":"LUCK","sector":"\u2014","price":411.18,"volume":1755561,"price_5d_ago":434.5,"pct_5d":-5.37,"pkr_5d":-23.32,"avg_vol_5d":1525440.0,"price_20d_ago":371.17,"pct_20d":10.78,"pkr_20d":40.01,"avg_vol_20d":2658294.0},{"symbol":"FFC","sector":"\u2014","price":509.16,"volume":1741665,"price_5d_ago":530.67,"pct_5d":-4.05,"pkr_5d":-21.51,"avg_vol_5d":1315591.0,"price_20d_ago":486.1,"pct_20d":4.74,"pkr_20d":23.06,"avg_vol_20d":1859270.0},{"symbol":"OGDC","sector":"\u2014","price":306.75,"volume":4885219,"price_5d_ago":327.0,"pct_5d":-6.19,"pkr_5d":-20.25,"avg_vol_5d":4113171.0,"price_20d_ago":270.59,"pct_20d":13.36,"pkr_20d":36.16,"avg_vol_20d":6714822.0}]}