{"date":"2026-07-07","total":4,"list1":[],"list2":[],"list3":[],"list4":[],"list5":[{"symbol":"KSE100","sector":"\u2014","price":186255.55,"volume":393645432,"price_5d_ago":180301.7,"pct_5d":3.3,"pkr_5d":5953.85,"avg_vol_5d":398262717.0,"price_20d_ago":170478.94,"pct_20d":9.25,"pkr_20d":15776.61,"avg_vol_20d":335928732.0},{"symbol":"ALLSHR","sector":"\u2014","price":112499.75,"volume":977818608,"price_5d_ago":108938.83,"pct_5d":3.27,"pkr_5d":3560.92,"avg_vol_5d":912602158.0,"price_20d_ago":102885.54,"pct_20d":9.34,"pkr_20d":9614.22,"avg_vol_20d":863163602.0},{"symbol":"PSXDIV20","sector":"\u2014","price":86027.39,"volume":107387415,"price_5d_ago":82833.13,"pct_5d":3.86,"pkr_5d":3194.27,"avg_vol_5d":94995492.0,"price_20d_ago":78177.63,"pct_20d":10.04,"pkr_20d":7849.76,"avg_vol_20d":63426390.0},{"symbol":"KSE30","sector":"\u2014","price":55672.44,"volume":178155130,"price_5d_ago":53716.04,"pct_5d":3.64,"pkr_5d":1956.4,"avg_vol_5d":170336839.0,"price_20d_ago":50877.61,"pct_20d":9.42,"pkr_20d":4794.82,"avg_vol_20d":153429114.0}],"list6":[]}